[
  {
    "title": "Create a Nav Bar in Svelte",
    "slug": "create-a-nav-bar-in-svelte",
    "markdown": "Let's create a Navbar component we can reuse in future projects.\r\n\r\nFirst, we'll create a `links` object that will be used for laying things out.\r\n```js\r\n<script>\r\n  export let links = [\r\n    {\r\n      name: 'posts',\r\n      url: 'posts',\r\n    },\r\n    {\r\n      name: 'home',\r\n      url: '.',\r\n    },\r\n    {\r\n      name: 'google',\r\n      url: 'https://www.google.com',\r\n    },\r\n    {\r\n      name: 'about',\r\n      url: 'about',\r\n    },\r\n  ];\r\n<script>\r\n```\r\nThen we can create our html using the links object\r\n```html\r\n<nav>\r\n  <ul>\r\n    {#each links as link}\r\n      <li>\r\n        <a  href={link.url}>{link.name}</a>\r\n      </li>\r\n    {/each}\r\n  </ul>\r\n</nav> \r\n```\r\nWhich should give us this...\r\n - posts\r\n - home\r\n - google\r\n - about \r\n\r\n With some styling, we can make it look like this:\r\n- posts\r\n- home\r\n- google\r\n- about\r\n{.ul-one}  \r\n\r\n\r\n",
    "css": ".ul-one {\r\n  display: flex;\r\n  flex: 1 1 auto;\r\n  margin: 0;\r\n  padding: 0;\r\n  justify-content: flex-end;\r\n  border: 1px solid #111\r\n}\r\n\r\n.ul-one li {\r\n  list-style: none;\r\n  text-decoration: none;\r\n  color: #111;\r\n  position: relative;\r\n  transition: all 0.4s ease;\r\n  padding: 0 0.5em 0.25em 0.5em;\r\n  cursor: pointer;\r\n}\r\n\r\n"
  },
  {
    "title": "Create a Nav Bar in Svelte is cool",
    "slug": "create-a-nav-bar-in-svelte-is-cool",
    "markdown": "Let's create a Navbar component we can reuse in future projects.\r\n\r\nFirst, we'll create a `links` object that will be used for laying things out.\r\n\r\n",
    "css": ".ul-one {\r\n  display: flex;\r\n  flex: 1 1 auto;\r\n  margin: 0;\r\n  padding: 0;\r\n  justify-content: flex-end;\r\n  border: 1px solid #111\r\n}\r\n\r\n.ul-one li {\r\n  list-style: none;\r\n  text-decoration: none;\r\n  color: #111;\r\n  position: relative;\r\n  transition: all 0.4s ease;\r\n  padding: 0 0.5em 0.25em 0.5em;\r\n  cursor: pointer;\r\n}\r\n\r\n"
  },
  {
    "title": "Create a Nav Bar in Svelte is neat",
    "slug": "create-a-nav-bar-in-svelte-is-neat",
    "markdown": "Let's create a Navbar component we can reuse in future projects.\r\n\r\nFirst, we'll create a `links` object that will be used for laying things out.\r\n```js\r\n<script>\r\n  export let links = [\r\n    {\r\n      name: 'posts',\r\n      url: 'posts',\r\n    },\r\n    {\r\n      name: 'home',\r\n      url: '.',\r\n    },\r\n    {\r\n      name: 'google',\r\n      url: 'https://www.google.com',\r\n    },\r\n    {\r\n      name: 'about',\r\n      url: 'about',\r\n    },\r\n  ];\r\n<script>\r\n```\r\nThen we can create our html using the links object\r\n```html\r\n<nav>\r\n  <ul>\r\n    {#each links as link}\r\n      <li>\r\n        <a  href={link.url}>{link.name}</a>\r\n      </li>\r\n    {/each}\r\n  </ul>\r\n</nav> \r\n```\r\n\r\n\r\n",
    "css": ".ul-one {\r\n  display: flex;\r\n  flex: 1 1 auto;\r\n  margin: 0;\r\n  padding: 0;\r\n  justify-content: flex-end;\r\n  border: 1px solid #111\r\n}\r\n\r\n.ul-one li {\r\n  list-style: none;\r\n  text-decoration: none;\r\n  color: #111;\r\n  position: relative;\r\n  transition: all 0.4s ease;\r\n  padding: 0 0.5em 0.25em 0.5em;\r\n  cursor: pointer;\r\n}\r\n\r\n"
  },
  {
    "title": "Create a Nav Bar in Svelte RAdical",
    "slug": "create-a-nav-bar-in-svelte-radical",
    "markdown": "Let's create a Navbar component we can reuse in future projects.\r\n\r\nFirst, we'll create a `links` object that will be used for laying things out.\r\n```js\r\n<script>\r\n  export let links = [\r\n    {\r\n      name: 'posts',\r\n      url: 'posts',\r\n    },\r\n    {\r\n      name: 'home',\r\n      url: '.',\r\n    },\r\n    {\r\n      name: 'google',\r\n      url: 'https://www.google.com',\r\n    },\r\n    {\r\n      name: 'about',\r\n      url: 'about',\r\n    },\r\n  ];\r\n<script>\r\n```\r\nThen we can create our html using the links object\r\n```html\r\n<nav>\r\n  <ul>\r\n    {#each links as link}\r\n      <li>\r\n        <a  href={link.url}>{link.name}</a>\r\n      </li>\r\n    {/each}\r\n  </ul>\r\n</nav> \r\n```\r\nWhich should give us this...\r\n - posts\r\n - home\r\n - google\r\n - about \r\n\r\n With some styling, we can make it look like this:\r\n- posts\r\n- home\r\n- google\r\n- about\r\n{.ul-one}  \r\n\r\n",
    "css": ".ul-one {\r\n  display: flex;\r\n  flex: 1 1 auto;\r\n  margin: 0;\r\n  padding: 0;\r\n  justify-content: flex-end;\r\n  border: 1px solid #111\r\n}\r\n\r\n.ul-one li {\r\n  list-style: none;\r\n  text-decoration: none;\r\n  color: #111;\r\n  position: relative;\r\n  transition: all 0.4s ease;\r\n  padding: 0 0.5em 0.25em 0.5em;\r\n  cursor: pointer;\r\n}\r\n\r\n",
    "timestamp": 1574914741705
  }
]